ftp_proxy_client.py
ftp_proxy_client-0.0.7.dist-info/DESCRIPTION.rst
ftp_proxy_client-0.0.7.dist-info/METADATA
ftp_proxy_client-0.0.7.dist-info/RECORD
ftp_proxy_client-0.0.7.dist-info/WHEEL
ftp_proxy_client-0.0.7.dist-info/metadata.json
ftp_proxy_client-0.0.7.dist-info/top_level.txt
