Metadata-Version: 2.0
Name: ftp-proxy-client
Version: 0.0.7
Summary: python client for ftp-proxy server
Home-page: https://github.com/uptilab2/ftp_proxy_client
Author: Emile Caron
Author-email: emile.caron@outlook.com
License: UNKNOWN
Project-URL: Source, https://github.com/uptilab2/ftp_proxy
Keywords: ftp proxy client
Platform: UNKNOWN
Classifier: Development Status :: 3 - Alpha
Classifier: Intended Audience :: Developers
Classifier: Topic :: Software Development :: Build Tools
Classifier: License :: OSI Approved :: MIT License
Classifier: Programming Language :: Python :: 3.6
Provides-Extra: dev
Requires-Dist: requests
Provides-Extra: dev
Requires-Dist: flake8; extra == 'dev'
